{
  "name": "STAR WARS™ Battlefront™ II",
  "platform": "Steam",
  "imageUrl": "",
  "description": "",
  "method": "Steam API",
  "appid": 1237950,
  "achievements": [
    {
      "name": "The Cleaner",
      "description": "",
      "imageUrl": "https://steamcdn-a.akamaihd.net/steamcommunity/public/images/apps/1237950/c1a36d69b51c348c24c26669c8d73bb82f33d317.jpg",
      "hidden": 1,
      "id": 0,
      "unlocked": false,
      "apiName": "Achievement_GOSCC_1",
      "getglobalpercentage": 42.6,
      "difficulty": 2
    },
    {
      "name": "The Battle of Endor",
      "description": "",
      "imageUrl": "https://steamcdn-a.akamaihd.net/steamcommunity/public/images/apps/1237950/baa536a63af111ea9ab20b034f59cd1011c8902c.jpg",
      "hidden": 1,
      "id": 1,
      "unlocked": false,
      "apiName": "Achievement_GOSCC_2",
      "getglobalpercentage": 35.2,
      "difficulty": 2
    },
    {
      "name": "The Dauntless",
      "description": "",
      "imageUrl": "https://steamcdn-a.akamaihd.net/steamcommunity/public/images/apps/1237950/08aaa360a1aa4d58f8085a9989524e0c5a19f98d.jpg",
      "hidden": 1,
      "id": 2,
      "unlocked": false,
      "apiName": "Achievement_GOSCC_3",
      "getglobalpercentage": 31.4,
      "difficulty": 2
    },
    {
      "name": "The Observatory",
      "description": "",
      "imageUrl": "https://steamcdn-a.akamaihd.net/steamcommunity/public/images/apps/1237950/4a223a72f0ab95658cdd088352a9ab36a14018af.jpg",
      "hidden": 1,
      "id": 3,
      "unlocked": false,
      "apiName": "Achievement_GOSCC_4",
      "getglobalpercentage": 30.1,
      "difficulty": 2
    },
    {
      "name": "The Storm",
      "description": "",
      "imageUrl": "https://steamcdn-a.akamaihd.net/steamcommunity/public/images/apps/1237950/d4ea4fcdade8246cb2987c02a2b2b862f3c425bd.jpg",
      "hidden": 1,
      "id": 4,
      "unlocked": false,
      "apiName": "Achievement_GOSCC_5",
      "getglobalpercentage": 27.9,
      "difficulty": 2
    },
    {
      "name": "Outcasts",
      "description": "",
      "imageUrl": "https://steamcdn-a.akamaihd.net/steamcommunity/public/images/apps/1237950/581c8a09f97afccd4db47086086a82b1e426f208.jpg",
      "hidden": 1,
      "id": 5,
      "unlocked": false,
      "apiName": "Achievement_GOSCC_6",
      "getglobalpercentage": 26.8,
      "difficulty": 2
    },
    {
      "name": "Royalty",
      "description": "",
      "imageUrl": "https://steamcdn-a.akamaihd.net/steamcommunity/public/images/apps/1237950/21e0ed00bf4aa9d8fd08969df60a0faf8574e1a9.jpg",
      "hidden": 1,
      "id": 6,
      "unlocked": false,
      "apiName": "Achievement_GOSCC_7",
      "getglobalpercentage": 26.1,
      "difficulty": 2
    },
    {
      "name": "General Distress",
      "description": "",
      "imageUrl": "https://steamcdn-a.akamaihd.net/steamcommunity/public/images/apps/1237950/8ef844f9d1b075acf12e9e48fe3b68d7b681f4e1.jpg",
      "hidden": 1,
      "id": 7,
      "unlocked": false,
      "apiName": "Achievement_GOSCC_8",
      "getglobalpercentage": 24.3,
      "difficulty": 2
    },
    {
      "name": "Under Covered Skies",
      "description": "",
      "imageUrl": "https://steamcdn-a.akamaihd.net/steamcommunity/public/images/apps/1237950/08a8568f9a6fe3bb757ae190317a646596ba1782.jpg",
      "hidden": 1,
      "id": 8,
      "unlocked": false,
      "apiName": "Achievement_GOSCC_9",
      "getglobalpercentage": 22.0,
      "difficulty": 2
    },
    {
      "name": "Cache Grab",
      "description": "",
      "imageUrl": "https://steamcdn-a.akamaihd.net/steamcommunity/public/images/apps/1237950/fe38c383eee7b0063aa422833cba9a8cb59d8871.jpg",
      "hidden": 1,
      "id": 9,
      "unlocked": false,
      "apiName": "Achievement_GOSCC_10",
      "getglobalpercentage": 21.0,
      "difficulty": 2
    },
    {
      "name": "The Battle of Jakku",
      "description": "",
      "imageUrl": "https://steamcdn-a.akamaihd.net/steamcommunity/public/images/apps/1237950/30361824ad208ba3e85c0091c1231cae48686b41.jpg",
      "hidden": 1,
      "id": 10,
      "unlocked": false,
      "apiName": "Achievement_GOSCC_11",
      "getglobalpercentage": 20.1,
      "difficulty": 2
    },
    {
      "name": "Until Ashes",
      "description": "",
      "imageUrl": "https://steamcdn-a.akamaihd.net/steamcommunity/public/images/apps/1237950/0c727b3538e850516390c8787874c1ce9c6b3b82.jpg",
      "hidden": 1,
      "id": 11,
      "unlocked": false,
      "apiName": "Achievement_GOSCC_12",
      "getglobalpercentage": 19.7,
      "difficulty": 3
    },
    {
      "name": "Discoveries",
      "description": "",
      "imageUrl": "https://steamcdn-a.akamaihd.net/steamcommunity/public/images/apps/1237950/5d93dec2bdfc0223aa9f05e198d07598e81e7461.jpg",
      "hidden": 1,
      "id": 12,
      "unlocked": false,
      "apiName": "Achievement_GOSCC_13",
      "getglobalpercentage": 19.2,
      "difficulty": 3
    },
    {
      "name": "Dark Forces",
      "description": "",
      "imageUrl": "https://steamcdn-a.akamaihd.net/steamcommunity/public/images/apps/1237950/028e2bc50213cf940e3ee354e394cafea6cd2c69.jpg",
      "hidden": 1,
      "id": 13,
      "unlocked": false,
      "apiName": "Achievement_GOSCC_14",
      "getglobalpercentage": 11.2,
      "difficulty": 3
    },
    {
      "name": "Balance Point",
      "description": "",
      "imageUrl": "https://steamcdn-a.akamaihd.net/steamcommunity/public/images/apps/1237950/49f4d6b3b57d2d30739cacfaf96d096e19bbd0ce.jpg",
      "hidden": 1,
      "id": 14,
      "unlocked": false,
      "apiName": "Achievement_GOSCC_15",
      "getglobalpercentage": 2.6,
      "difficulty": 4
    },
    {
      "name": "X-wing vs. TIE Fighter",
      "description": "",
      "imageUrl": "https://steamcdn-a.akamaihd.net/steamcommunity/public/images/apps/1237950/44a3df583b40ab191763394e9933692e025e90ae.jpg",
      "hidden": 1,
      "id": 15,
      "unlocked": false,
      "apiName": "Achievement_GOSCC_16",
      "getglobalpercentage": 14.2,
      "difficulty": 3
    },
    {
      "name": "Master of Deception",
      "description": "",
      "imageUrl": "https://steamcdn-a.akamaihd.net/steamcommunity/public/images/apps/1237950/f60518c49699c1f529fd623fece634ece61160c4.jpg",
      "hidden": 1,
      "id": 16,
      "unlocked": false,
      "apiName": "Achievement_GOSCC_17",
      "getglobalpercentage": 8.4,
      "difficulty": 3
    },
    {
      "name": "A Job Well Done",
      "description": "Complete 25 Multiplayer Milestones.",
      "imageUrl": "https://steamcdn-a.akamaihd.net/steamcommunity/public/images/apps/1237950/8b3e3ad6c2b0e463a180852e680bd2b2f471977d.jpg",
      "hidden": 0,
      "id": 17,
      "unlocked": false,
      "apiName": "Achievement_GOSCC_18",
      "getglobalpercentage": 24.9,
      "difficulty": 2
    },
    {
      "name": "Outbound Flight",
      "description": "Win a match of Starfighter Assault.",
      "imageUrl": "https://steamcdn-a.akamaihd.net/steamcommunity/public/images/apps/1237950/70cb4a3c9379aba48e9008a2f57ae02ee3965327.jpg",
      "hidden": 0,
      "id": 18,
      "unlocked": false,
      "apiName": "Achievement_GOSCC_19",
      "getglobalpercentage": 17.1,
      "difficulty": 3
    },
    {
      "name": "There Has Been An Awakening",
      "description": "Reach Rank 25.",
      "imageUrl": "https://steamcdn-a.akamaihd.net/steamcommunity/public/images/apps/1237950/084abfa45759e27531c9076e9a30a1a65b64b077.jpg",
      "hidden": 0,
      "id": 19,
      "unlocked": false,
      "apiName": "Achievement_GOSCC_20",
      "getglobalpercentage": 20.7,
      "difficulty": 2
    },
    {
      "name": "The Force is Strong With This One",
      "description": "Reach Rank 50.",
      "imageUrl": "https://steamcdn-a.akamaihd.net/steamcommunity/public/images/apps/1237950/daacfdf7329febcdc9e0b76362488ae7799a4743.jpg",
      "hidden": 0,
      "id": 20,
      "unlocked": false,
      "apiName": "Achievement_GOSCC_21",
      "getglobalpercentage": 5.0,
      "difficulty": 4
    },
    {
      "name": "Not All Miss",
      "description": "In Multiplayer, defeat 3 enemies within one Vanguard usage 5 times.",
      "imageUrl": "https://steamcdn-a.akamaihd.net/steamcommunity/public/images/apps/1237950/14ccb11e2d4d73eb5498dea612a42286a989481d.jpg",
      "hidden": 0,
      "id": 21,
      "unlocked": false,
      "apiName": "Achievement_GOSCC_22",
      "getglobalpercentage": 5.3,
      "difficulty": 3
    },
    {
      "name": "A Dominating Presence",
      "description": "In Multiplayer, boost 100 allies with the Officer commands.",
      "imageUrl": "https://steamcdn-a.akamaihd.net/steamcommunity/public/images/apps/1237950/9014b9e6c08ba6d2204cf50eaa7e5a0ddf773ce2.jpg",
      "hidden": 0,
      "id": 22,
      "unlocked": false,
      "apiName": "Achievement_GOSCC_23",
      "getglobalpercentage": 11.2,
      "difficulty": 3
    },
    {
      "name": "Sentry Mode Engaged",
      "description": "In Multiplayer, defeat 150 enemies with the Heavy's Sentry Gun.",
      "imageUrl": "https://steamcdn-a.akamaihd.net/steamcommunity/public/images/apps/1237950/058a68a483ff604e9425744c7fbc47884edf7567.jpg",
      "hidden": 0,
      "id": 23,
      "unlocked": false,
      "apiName": "Achievement_GOSCC_24",
      "getglobalpercentage": 10.4,
      "difficulty": 3
    },
    {
      "name": "Scoped",
      "description": "In Multiplayer, get 25 headshots with longblaster rifles.",
      "imageUrl": "https://steamcdn-a.akamaihd.net/steamcommunity/public/images/apps/1237950/f0710df6b8316a0c69cf9b729eb3f09ed480a684.jpg",
      "hidden": 0,
      "id": 24,
      "unlocked": false,
      "apiName": "Achievement_GOSCC_25",
      "getglobalpercentage": 16.0,
      "difficulty": 3
    },
    {
      "name": "The Interceptor",
      "description": "Get 20 Killstreaks with Interceptor ships.",
      "imageUrl": "https://steamcdn-a.akamaihd.net/steamcommunity/public/images/apps/1237950/c56e1daa0d606c4ba7d1e3be34d6e9aa158cae35.jpg",
      "hidden": 0,
      "id": 25,
      "unlocked": false,
      "apiName": "Achievement_GOSCC_26",
      "getglobalpercentage": 2.7,
      "difficulty": 4
    },
    {
      "name": "The Bomber",
      "description": "Defeat 50 enemies using Dual Proton Torpedoes with the Bomber ship class.",
      "imageUrl": "https://steamcdn-a.akamaihd.net/steamcommunity/public/images/apps/1237950/7b68042bed513044df92522fd102df3dbc45da9d.jpg",
      "hidden": 0,
      "id": 26,
      "unlocked": false,
      "apiName": "Achievement_GOSCC_27",
      "getglobalpercentage": 0.7,
      "difficulty": 4
    },
    {
      "name": "Multi-tasking",
      "description": "Defeat 25 Hero ships with Fighter ships.",
      "imageUrl": "https://steamcdn-a.akamaihd.net/steamcommunity/public/images/apps/1237950/28eb79a7ecdd275ca45176b4eed0c13464cda414.jpg",
      "hidden": 0,
      "id": 27,
      "unlocked": false,
      "apiName": "Achievement_GOSCC_28",
      "getglobalpercentage": 0.7,
      "difficulty": 4
    },
    {
      "name": "Complete Your Training",
      "description": "Complete all unique Battle Scenarios.",
      "imageUrl": "https://steamcdn-a.akamaihd.net/steamcommunity/public/images/apps/1237950/0b89d6569856eee6fd15503fe7404e15966d981b.jpg",
      "hidden": 0,
      "id": 28,
      "unlocked": false,
      "apiName": "Achievement_GOSCC_29",
      "getglobalpercentage": 4.1,
      "difficulty": 4
    },
    {
      "name": "There is No Such Thing As Luck",
      "description": "Engage in an Arcade match.",
      "imageUrl": "https://steamcdn-a.akamaihd.net/steamcommunity/public/images/apps/1237950/969d5823fd24ff2c13333f39e1e5efd4daecf7ed.jpg",
      "hidden": 0,
      "id": 29,
      "unlocked": false,
      "apiName": "Achievement_GOSCC_30",
      "getglobalpercentage": 22.2,
      "difficulty": 2
    },
    {
      "name": "Ignore Your Instincts At Your Peril",
      "description": "Destroy 25 objectives in Starfighter Assault.",
      "imageUrl": "https://steamcdn-a.akamaihd.net/steamcommunity/public/images/apps/1237950/aee594fbfc02c5ff862e8253d356d55907dfb71a.jpg",
      "hidden": 0,
      "id": 30,
      "unlocked": false,
      "apiName": "Achievement_GOSCC_31",
      "getglobalpercentage": 2.4,
      "difficulty": 4
    },
    {
      "name": "What a Blast",
      "description": "Win a match of Blast.",
      "imageUrl": "https://steamcdn-a.akamaihd.net/steamcommunity/public/images/apps/1237950/35d580f62948e1bbf87cd0dd35eac075fbb929ba.jpg",
      "hidden": 0,
      "id": 31,
      "unlocked": false,
      "apiName": "Achievement_GOSCC_32",
      "getglobalpercentage": 14.4,
      "difficulty": 3
    },
    {
      "name": "Strike Back",
      "description": "Win a match of Strike.",
      "imageUrl": "https://steamcdn-a.akamaihd.net/steamcommunity/public/images/apps/1237950/027caa39ac5028d64febb5e9f990a7a2f3ea2df9.jpg",
      "hidden": 0,
      "id": 32,
      "unlocked": false,
      "apiName": "Achievement_GOSCC_33",
      "getglobalpercentage": 7.5,
      "difficulty": 3
    },
    {
      "name": "Battle Beyond the Stars",
      "description": "Win a match of Galactic Assault.",
      "imageUrl": "https://steamcdn-a.akamaihd.net/steamcommunity/public/images/apps/1237950/d200d424aedc55bfa2348fea8cda3d1f1db5f5ff.jpg",
      "hidden": 0,
      "id": 33,
      "unlocked": false,
      "apiName": "Achievement_GOSCC_34",
      "getglobalpercentage": 39.0,
      "difficulty": 2
    },
    {
      "name": "Choose Your Path",
      "description": "Defeat 50 enemies in Heroes Vs Villains.",
      "imageUrl": "https://steamcdn-a.akamaihd.net/steamcommunity/public/images/apps/1237950/d23749afbadcac16cdf9199faaf3100c2963a748.jpg",
      "hidden": 0,
      "id": 34,
      "unlocked": false,
      "apiName": "Achievement_GOSCC_35",
      "getglobalpercentage": 11.6,
      "difficulty": 3
    },
    {
      "name": "Quick Strike",
      "description": "Be the first one to defeat an enemy in a Multiplayer match.",
      "imageUrl": "https://steamcdn-a.akamaihd.net/steamcommunity/public/images/apps/1237950/0246a551199752e13be01f9b3b1e57eac82bd209.jpg",
      "hidden": 0,
      "id": 35,
      "unlocked": false,
      "apiName": "Achievement_GOSCC_36",
      "getglobalpercentage": 40.6,
      "difficulty": 2
    },
    {
      "name": "Heavy is the Hand",
      "description": "Win a match of Heroes vs Villains",
      "imageUrl": "https://steamcdn-a.akamaihd.net/steamcommunity/public/images/apps/1237950/9354c437ff2e5be223d2ea8f9789ba89dc66d753.jpg",
      "hidden": 0,
      "id": 36,
      "unlocked": false,
      "apiName": "Achievement_GOSCC_37",
      "getglobalpercentage": 24.1,
      "difficulty": 2
    },
    {
      "name": "Do. Or Do Not. There is no Try.",
      "description": "Play as all launch heroes in Multiplayer.",
      "imageUrl": "https://steamcdn-a.akamaihd.net/steamcommunity/public/images/apps/1237950/4e4d62d830f0981ee3704b5655b2d3214ce791f7.jpg",
      "hidden": 0,
      "id": 37,
      "unlocked": false,
      "apiName": "Achievement_GOSCC_38",
      "getglobalpercentage": 6.3,
      "difficulty": 3
    },
    {
      "name": "A Galaxy at War",
      "description": "Win one match in each Multiplayer game mode.",
      "imageUrl": "https://steamcdn-a.akamaihd.net/steamcommunity/public/images/apps/1237950/f547816e01d1785913965da5b0e8809b609bc909.jpg",
      "hidden": 0,
      "id": 38,
      "unlocked": false,
      "apiName": "Achievement_GOSCC_39",
      "getglobalpercentage": 2.3,
      "difficulty": 4
    },
    {
      "name": "We are the Spark",
      "description": "Defeat 500 enemies as a hero on any Multiplayer map.",
      "imageUrl": "https://steamcdn-a.akamaihd.net/steamcommunity/public/images/apps/1237950/a78ca4acacc4c4eb8586cc27f69a355ed4cc2488.jpg",
      "hidden": 0,
      "id": 39,
      "unlocked": false,
      "apiName": "Achievement_GOSCC_40",
      "getglobalpercentage": 13.1,
      "difficulty": 3
    },
    {
      "name": "Project: Resurrection",
      "description": "",
      "imageUrl": "https://steamcdn-a.akamaihd.net/steamcommunity/public/images/apps/1237950/b464e3800c482f32fd13b7837a31d6d36fdc74ef.jpg",
      "hidden": 1,
      "id": 40,
      "unlocked": false,
      "apiName": "Achievement_GOSCC_41",
      "getglobalpercentage": 13.7,
      "difficulty": 3
    },
    {
      "name": "Ashes of the Empire",
      "description": "",
      "imageUrl": "https://steamcdn-a.akamaihd.net/steamcommunity/public/images/apps/1237950/cf030768782dbea0d5dc9c34ff6568a230615279.jpg",
      "hidden": 1,
      "id": 41,
      "unlocked": false,
      "apiName": "Achievement_GOSCC_42",
      "getglobalpercentage": 12.9,
      "difficulty": 3
    },
    {
      "name": "Inferno",
      "description": "",
      "imageUrl": "https://steamcdn-a.akamaihd.net/steamcommunity/public/images/apps/1237950/9556a879c9564045c750de1d305b435f47010e57.jpg",
      "hidden": 1,
      "id": 42,
      "unlocked": false,
      "apiName": "Achievement_GOSCC_43",
      "getglobalpercentage": 12.1,
      "difficulty": 3
    }
  ]
}