{
  "name": "Kraken",
  "platform": "Steam",
  "imageUrl": "",
  "description": "",
  "method": "Steam API",
  "appid": 356190,
  "achievements": [
    {
      "name": "Forger",
      "description": "Forge a higher-quality Gem by combining three Gems of the same quality.",
      "imageUrl": "https://steamcdn-a.akamaihd.net/steamcommunity/public/images/apps/356190/b15e92209a7483aee045444b7b1cd3439ea787de.jpg",
      "hidden": 0,
      "id": 0,
      "unlocked": false,
      "apiName": "GemForge",
      "getglobalpercentage": 58.7,
      "difficulty": 1
    },
    {
      "name": "Rule of Three",
      "description": "Unlock 3 Gem slots.",
      "imageUrl": "https://steamcdn-a.akamaihd.net/steamcommunity/public/images/apps/356190/517613fdc54a543c849125ab7071ee3d6822fe2f.jpg",
      "hidden": 0,
      "id": 1,
      "unlocked": false,
      "apiName": "GemSlotsUnlocked",
      "getglobalpercentage": 61.6,
      "difficulty": 1
    },
    {
      "name": "Best Defense",
      "description": "Equip 3 Siege Upgrades on an Assault Team.",
      "imageUrl": "https://steamcdn-a.akamaihd.net/steamcommunity/public/images/apps/356190/522b686a6f1853bfe64f73de5a0ca4e11794bd73.jpg",
      "hidden": 0,
      "id": 2,
      "unlocked": false,
      "apiName": "WarUpgradesEquipped",
      "getglobalpercentage": 46.1,
      "difficulty": 2
    },
    {
      "name": "Fit for War",
      "description": "Complete a challenge to upgrade a piece of gear.",
      "imageUrl": "https://steamcdn-a.akamaihd.net/steamcommunity/public/images/apps/356190/abe61a80c8c77da47ebb3b777ec9cc17956b43fe.jpg",
      "hidden": 0,
      "id": 3,
      "unlocked": false,
      "apiName": "EquipmentUpgraded",
      "getglobalpercentage": 62.2,
      "difficulty": 1
    },
    {
      "name": "Hostile Takeover",
      "description": "Defeat a Warchief.",
      "imageUrl": "https://steamcdn-a.akamaihd.net/steamcommunity/public/images/apps/356190/c58794622f3c8b7ab7938425ea07592d46e82448.jpg",
      "hidden": 0,
      "id": 4,
      "unlocked": false,
      "apiName": "WarchiefDefeated",
      "getglobalpercentage": 62.1,
      "difficulty": 1
    },
    {
      "name": "Vandal",
      "description": "Destroy a Monument.",
      "imageUrl": "https://steamcdn-a.akamaihd.net/steamcommunity/public/images/apps/356190/28234bcea2ca477e55f4a2e718cc2b60a3841698.jpg",
      "hidden": 0,
      "id": 5,
      "unlocked": false,
      "apiName": "MonumentDestoyed",
      "getglobalpercentage": 60.1,
      "difficulty": 1
    },
    {
      "name": "Speak Friend and Enter",
      "description": "Open one of the Ithildin Doors.",
      "imageUrl": "https://steamcdn-a.akamaihd.net/steamcommunity/public/images/apps/356190/509d76f3313f24d498c372f660534f704de64b0f.jpg",
      "hidden": 0,
      "id": 6,
      "unlocked": false,
      "apiName": "IthildinDoorOpened",
      "getglobalpercentage": 48.0,
      "difficulty": 2
    },
    {
      "name": "Bound by Blood",
      "description": "Complete an Online Vendetta.",
      "imageUrl": "https://steamcdn-a.akamaihd.net/steamcommunity/public/images/apps/356190/f7b7ebf3f60fac3cbf78a916cb79dbf248b78ec9.jpg",
      "hidden": 0,
      "id": 7,
      "unlocked": false,
      "apiName": "BountyCompleted",
      "getglobalpercentage": 45.3,
      "difficulty": 2
    },
    {
      "name": "Avenged",
      "description": "Complete a Vendetta Mission.",
      "imageUrl": "https://steamcdn-a.akamaihd.net/steamcommunity/public/images/apps/356190/9464e0f03c2520240e79b5f77d3f43159d6084fd.jpg",
      "hidden": 0,
      "id": 8,
      "unlocked": false,
      "apiName": "VendettaCompleted",
      "getglobalpercentage": 63.4,
      "difficulty": 1
    },
    {
      "name": "Master Forger",
      "description": "Forge a top tier Gem.",
      "imageUrl": "https://steamcdn-a.akamaihd.net/steamcommunity/public/images/apps/356190/11d86e234bedb8159847b1cb272f2c2adb89a9b4.jpg",
      "hidden": 0,
      "id": 9,
      "unlocked": false,
      "apiName": "TopTierGemForged",
      "getglobalpercentage": 23.0,
      "difficulty": 2
    },
    {
      "name": "Promise Keeper",
      "description": "Issue a Death Threat, and then successfully kill the target.",
      "imageUrl": "https://steamcdn-a.akamaihd.net/steamcommunity/public/images/apps/356190/72cd4721c4d7c9f91f2cd5d0098240b2b7c18c30.jpg",
      "hidden": 0,
      "id": 10,
      "unlocked": false,
      "apiName": "DeathThreatMission",
      "getglobalpercentage": 36.8,
      "difficulty": 2
    },
    {
      "name": "Death is not the End",
      "description": "Resurrect a Follower Captain.",
      "imageUrl": "https://steamcdn-a.akamaihd.net/steamcommunity/public/images/apps/356190/f520eec0f27b0cd5f301d1d18ae4ecb96de0a681.jpg",
      "hidden": 0,
      "id": 11,
      "unlocked": false,
      "apiName": "FollowerResurrect",
      "getglobalpercentage": 9.3,
      "difficulty": 3
    },
    {
      "name": "Dismantled",
      "description": "Disable an Outpost.",
      "imageUrl": "https://steamcdn-a.akamaihd.net/steamcommunity/public/images/apps/356190/28f6ff986c2405e0573307e01df4f51486c152d2.jpg",
      "hidden": 0,
      "id": 12,
      "unlocked": false,
      "apiName": "OutpostDisabled",
      "getglobalpercentage": 61.0,
      "difficulty": 1
    },
    {
      "name": "Banished",
      "description": "",
      "imageUrl": "https://steamcdn-a.akamaihd.net/steamcommunity/public/images/apps/356190/826ac280e4b0f64c68800338687a052d7cb58961.jpg",
      "hidden": 1,
      "id": 13,
      "unlocked": false,
      "apiName": "SuladanDefeated",
      "getglobalpercentage": 36.3,
      "difficulty": 2
    },
    {
      "name": "Brought to Heel",
      "description": "",
      "imageUrl": "https://steamcdn-a.akamaihd.net/steamcommunity/public/images/apps/356190/04637dac751f35dc8715d076d0602de940dc5394.jpg",
      "hidden": 1,
      "id": 14,
      "unlocked": false,
      "apiName": "HelmHammerhandDefeated",
      "getglobalpercentage": 32.8,
      "difficulty": 2
    },
    {
      "name": "Lord of Horror",
      "description": "",
      "imageUrl": "https://steamcdn-a.akamaihd.net/steamcommunity/public/images/apps/356190/4cce6c55997726198b514b02c1bae220972f3b5b.jpg",
      "hidden": 1,
      "id": 15,
      "unlocked": false,
      "apiName": "BalrogDefeated",
      "getglobalpercentage": 36.6,
      "difficulty": 2
    },
    {
      "name": "Finished Tales",
      "description": "Recover all Gondorian artifacts.",
      "imageUrl": "https://steamcdn-a.akamaihd.net/steamcommunity/public/images/apps/356190/8cd317336a262d74ec95cab062666995c87fc880.jpg",
      "hidden": 0,
      "id": 16,
      "unlocked": false,
      "apiName": "GondorArtifacts",
      "getglobalpercentage": 16.1,
      "difficulty": 3
    },
    {
      "name": "The Web Revealed",
      "description": "Uncover the final Shelob memory and reveal the Web of Fate.",
      "imageUrl": "https://steamcdn-a.akamaihd.net/steamcommunity/public/images/apps/356190/d258da9e34ae62ede1b72ea3c6d1e76cd07c9a50.jpg",
      "hidden": 0,
      "id": 17,
      "unlocked": false,
      "apiName": "ShelobComplete",
      "getglobalpercentage": 20.0,
      "difficulty": 3
    },
    {
      "name": "What Once Was Lost",
      "description": "",
      "imageUrl": "https://steamcdn-a.akamaihd.net/steamcommunity/public/images/apps/356190/9ca0c44e669432cdd1c78f5a090d28e10aeef359.jpg",
      "hidden": 1,
      "id": 18,
      "unlocked": false,
      "apiName": "Act1Complete",
      "getglobalpercentage": 57.9,
      "difficulty": 1
    },
    {
      "name": "First Steps",
      "description": "",
      "imageUrl": "https://steamcdn-a.akamaihd.net/steamcommunity/public/images/apps/356190/b26256defbf3b6d313702500fa5afc85f6079ce6.jpg",
      "hidden": 1,
      "id": 19,
      "unlocked": false,
      "apiName": "Ratbag1Complete",
      "getglobalpercentage": 53.0,
      "difficulty": 1
    },
    {
      "name": "Peace in Death",
      "description": "",
      "imageUrl": "https://steamcdn-a.akamaihd.net/steamcommunity/public/images/apps/356190/a02ae5633f110f0661f090915af07ad213fe9066.jpg",
      "hidden": 1,
      "id": 20,
      "unlocked": false,
      "apiName": "ShadowWarComplete",
      "getglobalpercentage": 14.3,
      "difficulty": 3
    },
    {
      "name": "Undeath Defeats Undeath",
      "description": "",
      "imageUrl": "https://steamcdn-a.akamaihd.net/steamcommunity/public/images/apps/356190/9f83816e928e3eea8aedb5b94fa0732c36325ea2.jpg",
      "hidden": 1,
      "id": 21,
      "unlocked": false,
      "apiName": "CarnanComplete",
      "getglobalpercentage": 26.0,
      "difficulty": 2
    },
    {
      "name": "Fall and Rise",
      "description": "",
      "imageUrl": "https://steamcdn-a.akamaihd.net/steamcommunity/public/images/apps/356190/6379e59ce7cc8b9d88086e9c0197340411bfed3f.jpg",
      "hidden": 1,
      "id": 22,
      "unlocked": false,
      "apiName": "RatbagComplete",
      "getglobalpercentage": 30.2,
      "difficulty": 2
    },
    {
      "name": "No Orc Lives Forever",
      "description": "Win all Fight Pit missions.",
      "imageUrl": "https://steamcdn-a.akamaihd.net/steamcommunity/public/images/apps/356190/a7d778476825876805c899d74cdf311ef707c17e.jpg",
      "hidden": 0,
      "id": 23,
      "unlocked": false,
      "apiName": "OrcArenasComplete",
      "getglobalpercentage": 8.3,
      "difficulty": 3
    },
    {
      "name": "Forged by War",
      "description": "Unlock all player skills.",
      "imageUrl": "https://steamcdn-a.akamaihd.net/steamcommunity/public/images/apps/356190/59f74fd6f69bb885868f4eb9c8e3a260315e8e36.jpg",
      "hidden": 0,
      "id": 24,
      "unlocked": false,
      "apiName": "PlayerSkillsUnlocked",
      "getglobalpercentage": 26.8,
      "difficulty": 2
    },
    {
      "name": "Purge",
      "description": "Purify all the Haedir.",
      "imageUrl": "https://steamcdn-a.akamaihd.net/steamcommunity/public/images/apps/356190/fa6cc493b5c7154af334bf8c471b87af1cdfe7b4.jpg",
      "hidden": 0,
      "id": 25,
      "unlocked": false,
      "apiName": "PurifiedHaedir",
      "getglobalpercentage": 31.5,
      "difficulty": 2
    },
    {
      "name": "Stalemate is Victory",
      "description": "",
      "imageUrl": "https://steamcdn-a.akamaihd.net/steamcommunity/public/images/apps/356190/c1c2cfb186896c520c8657ad1eb827e99e517692.jpg",
      "hidden": 1,
      "id": 26,
      "unlocked": false,
      "apiName": "WitchKingMorgul",
      "getglobalpercentage": 28.3,
      "difficulty": 2
    },
    {
      "name": "The Operative",
      "description": "Turn all of a Warchief's bodyguards (minimum 2) into spies, then confront him.",
      "imageUrl": "https://steamcdn-a.akamaihd.net/steamcommunity/public/images/apps/356190/aed0a0882ece4f2f34ef94c45bb0190f73b6d5a7.jpg",
      "hidden": 0,
      "id": 27,
      "unlocked": false,
      "apiName": "WarchiefsSpies",
      "getglobalpercentage": 33.0,
      "difficulty": 2
    },
    {
      "name": "Such Great Heights",
      "description": "Reach the rank of Captain in Online Conquest.",
      "imageUrl": "https://steamcdn-a.akamaihd.net/steamcommunity/public/images/apps/356190/d866ef4a18fc8da243961ee2b81239ba0e9fede1.jpg",
      "hidden": 0,
      "id": 28,
      "unlocked": false,
      "apiName": "ConquestRank",
      "getglobalpercentage": 5.9,
      "difficulty": 3
    },
    {
      "name": "No Orc Left Behind",
      "description": "Rescue a Follower who's been captured.",
      "imageUrl": "https://steamcdn-a.akamaihd.net/steamcommunity/public/images/apps/356190/f1c4614f4b2075dfa3be9e5fc339f517aa106a78.jpg",
      "hidden": 0,
      "id": 29,
      "unlocked": false,
      "apiName": "CaptiveRescued",
      "getglobalpercentage": 22.0,
      "difficulty": 2
    },
    {
      "name": "Better Luck Next Time",
      "description": "Meet an Enemy or a Follower who has cheated death.",
      "imageUrl": "https://steamcdn-a.akamaihd.net/steamcommunity/public/images/apps/356190/8cb1ba9e667b2c550311bc3204d0a2753b53a058.jpg",
      "hidden": 0,
      "id": 30,
      "unlocked": false,
      "apiName": "DeathCheater",
      "getglobalpercentage": 72.7,
      "difficulty": 1
    },
    {
      "name": "It Came From Within",
      "description": "Start a Conquest with all Warchiefs as spies.",
      "imageUrl": "https://steamcdn-a.akamaihd.net/steamcommunity/public/images/apps/356190/5b9b16c7a52893bb7397692c0b72f244c032f4b4.jpg",
      "hidden": 0,
      "id": 31,
      "unlocked": false,
      "apiName": "FortAssaultSpies",
      "getglobalpercentage": 16.7,
      "difficulty": 3
    },
    {
      "name": "Power Couple",
      "description": "Send a Follower to support another Follower in a Nemesis Mission.",
      "imageUrl": "https://steamcdn-a.akamaihd.net/steamcommunity/public/images/apps/356190/8b9152d349e57fe808445734bee301f7e2b50dbd.jpg",
      "hidden": 0,
      "id": 32,
      "unlocked": false,
      "apiName": "FollowerSupport",
      "getglobalpercentage": 37.6,
      "difficulty": 2
    },
    {
      "name": "Everything is Permitted",
      "description": "Shame an Assassin until he becomes deranged.",
      "imageUrl": "https://steamcdn-a.akamaihd.net/steamcommunity/public/images/apps/356190/b6d5c62cfb401e1e040ef5c212e2bffc62414a14.jpg",
      "hidden": 0,
      "id": 33,
      "unlocked": false,
      "apiName": "DerangedShame",
      "getglobalpercentage": 13.8,
      "difficulty": 3
    },
    {
      "name": "Life of the Party\t",
      "description": "Send a Destroyer on a Vendetta Mission.",
      "imageUrl": "https://steamcdn-a.akamaihd.net/steamcommunity/public/images/apps/356190/2bd8d1ea4dfb208e7bff4d728f69e0b0e19e7b30.jpg",
      "hidden": 0,
      "id": 34,
      "unlocked": false,
      "apiName": "FeastDestroyer",
      "getglobalpercentage": 7.7,
      "difficulty": 3
    },
    {
      "name": "If You Can't Beat Them",
      "description": "Recruit an Orc after he's killed you three or more times.",
      "imageUrl": "https://steamcdn-a.akamaihd.net/steamcommunity/public/images/apps/356190/575842dbdb2015faae918cab38056a9598985420.jpg",
      "hidden": 0,
      "id": 35,
      "unlocked": false,
      "apiName": "DominateNemesis",
      "getglobalpercentage": 4.2,
      "difficulty": 4
    },
    {
      "name": "I Like to Watch",
      "description": "Watch a Follower murder another Captain without helping him.",
      "imageUrl": "https://steamcdn-a.akamaihd.net/steamcommunity/public/images/apps/356190/fe88cad21c79f570ff6557d68ddd6901c7aed833.jpg",
      "hidden": 0,
      "id": 36,
      "unlocked": false,
      "apiName": "FollowerKill",
      "getglobalpercentage": 54.0,
      "difficulty": 1
    },
    {
      "name": "Second Age Warrior",
      "description": "Complete all Shadow of the Past missions in one region.",
      "imageUrl": "https://steamcdn-a.akamaihd.net/steamcommunity/public/images/apps/356190/63be722726ca77f9ccf17fcb7d2901a04c800fe8.jpg",
      "hidden": 0,
      "id": 37,
      "unlocked": false,
      "apiName": "SOTPRegion",
      "getglobalpercentage": 21.3,
      "difficulty": 2
    },
    {
      "name": "Rough Rider",
      "description": "Ride every type of beast and rare beast.",
      "imageUrl": "https://steamcdn-a.akamaihd.net/steamcommunity/public/images/apps/356190/c5ce5929194d5b26f4fad29647e62fe968614599.jpg",
      "hidden": 0,
      "id": 38,
      "unlocked": false,
      "apiName": "AllBeastsRidden",
      "getglobalpercentage": 9.3,
      "difficulty": 3
    },
    {
      "name": "Wild Things",
      "description": "Kill a drake while riding a graug.",
      "imageUrl": "https://steamcdn-a.akamaihd.net/steamcommunity/public/images/apps/356190/317f7b30da73dda7f0629704be589d01d4749cf6.jpg",
      "hidden": 0,
      "id": 39,
      "unlocked": false,
      "apiName": "DrakesKilledWithGraug",
      "getglobalpercentage": 3.3,
      "difficulty": 4
    },
    {
      "name": "Trolling",
      "description": "Kill a Captain while riding an Olog.",
      "imageUrl": "https://steamcdn-a.akamaihd.net/steamcommunity/public/images/apps/356190/3789aeb2e8c7735e66660798eb70ecbe77d3b84e.jpg",
      "hidden": 0,
      "id": 40,
      "unlocked": false,
      "apiName": "CaptainKilledWithOlog",
      "getglobalpercentage": 3.3,
      "difficulty": 4
    },
    {
      "name": "Vertical Mobility",
      "description": "Help a grunt become an Overlord.",
      "imageUrl": "https://steamcdn-a.akamaihd.net/steamcommunity/public/images/apps/356190/e5a1255bf7d1fb774fb49e4a576ab9b82284fe41.jpg",
      "hidden": 0,
      "id": 41,
      "unlocked": false,
      "apiName": "GruntOverlord",
      "getglobalpercentage": 11.5,
      "difficulty": 3
    },
    {
      "name": "Blood on Blood",
      "description": "Make a Captain kill his bloodbrother.",
      "imageUrl": "https://steamcdn-a.akamaihd.net/steamcommunity/public/images/apps/356190/5c911d312102a02228a3d1876e56e69626622659.jpg",
      "hidden": 0,
      "id": 42,
      "unlocked": false,
      "apiName": "CaptainKillsBloodbrother",
      "getglobalpercentage": 7.4,
      "difficulty": 3
    },
    {
      "name": "Nemesis",
      "description": "Encounter the same Orc 3 times in nemesis missions without killing him.",
      "imageUrl": "https://steamcdn-a.akamaihd.net/steamcommunity/public/images/apps/356190/eba1df1293e0cc737ee8411f0ad851f8f4be3821.jpg",
      "hidden": 0,
      "id": 43,
      "unlocked": false,
      "apiName": "MulitFleeCaptain",
      "getglobalpercentage": 43.0,
      "difficulty": 2
    },
    {
      "name": "Feed the Beasts",
      "description": "Attract every kind of beast using bait.",
      "imageUrl": "https://steamcdn-a.akamaihd.net/steamcommunity/public/images/apps/356190/cf585dc8d37a939f2532b0c4bcec5f8f4fcf1b5f.jpg",
      "hidden": 0,
      "id": 44,
      "unlocked": false,
      "apiName": "AllBeastBait",
      "getglobalpercentage": 38.0,
      "difficulty": 2
    },
    {
      "name": "Bad Boss",
      "description": "Strike a Follower until he's had enough.",
      "imageUrl": "https://steamcdn-a.akamaihd.net/steamcommunity/public/images/apps/356190/30918f1867e136f034cf05497a999ff0ca21eb39.jpg",
      "hidden": 0,
      "id": 45,
      "unlocked": false,
      "apiName": "BetrayFollower",
      "getglobalpercentage": 8.8,
      "difficulty": 3
    },
    {
      "name": "The Stuff of Legend",
      "description": "Equip a full Legendary Gear set as Talion.",
      "imageUrl": "https://steamcdn-a.akamaihd.net/steamcommunity/public/images/apps/356190/3f97c9e00908d0ba045a9b400072c67c4e93868f.jpg",
      "hidden": 0,
      "id": 46,
      "unlocked": false,
      "apiName": "GearCollected",
      "getglobalpercentage": 29.1,
      "difficulty": 2
    },
    {
      "name": "Follower Perks",
      "description": "Use a Training Order to give a Follower a gang.",
      "imageUrl": "https://steamcdn-a.akamaihd.net/steamcommunity/public/images/apps/356190/a72c40a7ce9afadce66f05d169b32a6731f084a4.jpg",
      "hidden": 0,
      "id": 47,
      "unlocked": false,
      "apiName": "ContractGang",
      "getglobalpercentage": 34.7,
      "difficulty": 2
    },
    {
      "name": "Overkill",
      "description": "Send a Follower to kill another Follower in a pit fight.",
      "imageUrl": "https://steamcdn-a.akamaihd.net/steamcommunity/public/images/apps/356190/6bac6edfd6e67f833a42ea117dd25a7dd22cdcdf.jpg",
      "hidden": 0,
      "id": 48,
      "unlocked": false,
      "apiName": "FollowerKillFollower",
      "getglobalpercentage": 11.2,
      "difficulty": 3
    },
    {
      "name": "Headhunter",
      "description": "Recruit a Follower of every Advanced Class.",
      "imageUrl": "https://steamcdn-a.akamaihd.net/steamcommunity/public/images/apps/356190/cb1a00820e8225b208298850dca82376041c110c.jpg",
      "hidden": 0,
      "id": 49,
      "unlocked": false,
      "apiName": "AllAdvancedRecruitment",
      "getglobalpercentage": 43.9,
      "difficulty": 2
    },
    {
      "name": "For Gondor",
      "description": "",
      "imageUrl": "https://steamcdn-a.akamaihd.net/steamcommunity/public/images/apps/356190/d731af5056919ada731278fc628a497cc836774b.jpg",
      "hidden": 1,
      "id": 50,
      "unlocked": false,
      "apiName": "GondorCompleted",
      "getglobalpercentage": 35.8,
      "difficulty": 2
    },
    {
      "name": "Banish the Darkness",
      "description": "",
      "imageUrl": "https://steamcdn-a.akamaihd.net/steamcommunity/public/images/apps/356190/dead0b5f20e0f44e41197bb4322d53092aff4383.jpg",
      "hidden": 1,
      "id": 51,
      "unlocked": false,
      "apiName": "BladeCompleted",
      "getglobalpercentage": 25.2,
      "difficulty": 2
    },
    {
      "name": "Flash Mob",
      "description": "Blind 100 Orcs.",
      "imageUrl": "https://steamcdn-a.akamaihd.net/steamcommunity/public/images/apps/356190/068672b875368e91fd01635392dd57c8b16d506c.jpg",
      "hidden": 0,
      "id": 52,
      "unlocked": false,
      "apiName": "BlindOrcs",
      "getglobalpercentage": 10.5,
      "difficulty": 3
    },
    {
      "name": "Banished Ambition",
      "description": "Defeat the Rogue Nazgûl.",
      "imageUrl": "https://steamcdn-a.akamaihd.net/steamcommunity/public/images/apps/356190/68ac8307675d71888de676af5091e72b4911aae9.jpg",
      "hidden": 0,
      "id": 53,
      "unlocked": false,
      "apiName": "DLC3Volcano",
      "getglobalpercentage": 8.1,
      "difficulty": 3
    },
    {
      "name": "Scorched Earth",
      "description": "Deny Sauron’s control of Seregost forever.",
      "imageUrl": "https://steamcdn-a.akamaihd.net/steamcommunity/public/images/apps/356190/d0c1957d3d52acd9473101be0e8cf043a246d08f.jpg",
      "hidden": 0,
      "id": 54,
      "unlocked": false,
      "apiName": "DLC3SnowMtn",
      "getglobalpercentage": 9.1,
      "difficulty": 3
    },
    {
      "name": "Holding the Line",
      "description": "Defend Cirith Ungol from a new threat.",
      "imageUrl": "https://steamcdn-a.akamaihd.net/steamcommunity/public/images/apps/356190/47029056ae0519284b2fc86cfe05999f9a05f3ac.jpg",
      "hidden": 0,
      "id": 55,
      "unlocked": false,
      "apiName": "DLC3MtnPass",
      "getglobalpercentage": 10.8,
      "difficulty": 3
    },
    {
      "name": "Problem Solved",
      "description": "Settle the Fixer’s score with the overlord of Núrn.",
      "imageUrl": "https://steamcdn-a.akamaihd.net/steamcommunity/public/images/apps/356190/67bce53a851d1cfb4e024b6de64bfda1c981172a.jpg",
      "hidden": 0,
      "id": 56,
      "unlocked": false,
      "apiName": "DLC3Island",
      "getglobalpercentage": 8.5,
      "difficulty": 3
    },
    {
      "name": "The Time has Come",
      "description": "Witness the end of Eltariel’s path.",
      "imageUrl": "https://steamcdn-a.akamaihd.net/steamcommunity/public/images/apps/356190/8f2ca27f5568787532fae7cb7c1d9b2b0ac3cf07.jpg",
      "hidden": 0,
      "id": 57,
      "unlocked": false,
      "apiName": "DLC3Finale",
      "getglobalpercentage": 8.0,
      "difficulty": 3
    },
    {
      "name": "Elven Conquest",
      "description": "Complete an Online Conquest with an Eltariel skin.",
      "imageUrl": "https://steamcdn-a.akamaihd.net/steamcommunity/public/images/apps/356190/1c5ab3e7f1eaa92866040da0ef9f6b8d772a4a8c.jpg",
      "hidden": 0,
      "id": 58,
      "unlocked": false,
      "apiName": "DLC3OnlineConquest",
      "getglobalpercentage": 3.9,
      "difficulty": 4
    },
    {
      "name": "I See the Light",
      "description": "Use Light Trap against 20 Orcs.",
      "imageUrl": "https://steamcdn-a.akamaihd.net/steamcommunity/public/images/apps/356190/d0b41ee8b0a8817d031efa2565f0237c73af71e4.jpg",
      "hidden": 0,
      "id": 59,
      "unlocked": false,
      "apiName": "DLC3LightTraps",
      "getglobalpercentage": 2.8,
      "difficulty": 4
    },
    {
      "name": "Complete in Defeat",
      "description": "Defeat the Lawless.",
      "imageUrl": "https://steamcdn-a.akamaihd.net/steamcommunity/public/images/apps/356190/254916bd7a75b529ec7f02f76495704a00692411.jpg",
      "hidden": 0,
      "id": 60,
      "unlocked": false,
      "apiName": "DLC3GearChallenges",
      "getglobalpercentage": 5.6,
      "difficulty": 3
    },
    {
      "name": "Unlikely Alliances",
      "description": "Recruit your first follower as Eltariel.",
      "imageUrl": "https://steamcdn-a.akamaihd.net/steamcommunity/public/images/apps/356190/1cb9d0b994925b07c02f86bf17c9831d8f3f9a80.jpg",
      "hidden": 0,
      "id": 61,
      "unlocked": false,
      "apiName": "EltarielRecruitFollower",
      "getglobalpercentage": 12.6,
      "difficulty": 3
    },
    {
      "name": "No Way Out",
      "description": "Change the landscape of Lithlad.",
      "imageUrl": "https://steamcdn-a.akamaihd.net/steamcommunity/public/images/apps/356190/9eca9be8a2c33addcb4a69a43cd7f858fd525fd6.jpg",
      "hidden": 0,
      "id": 62,
      "unlocked": false,
      "apiName": "DLC4Canyon",
      "getglobalpercentage": 8.7,
      "difficulty": 3
    },
    {
      "name": "Belly of the Beast",
      "description": "Leave your mark on the Overlord of Lithlad.",
      "imageUrl": "https://steamcdn-a.akamaihd.net/steamcommunity/public/images/apps/356190/9bd47285594c8854d8491b7152d60570e72c2a0c.jpg",
      "hidden": 0,
      "id": 63,
      "unlocked": false,
      "apiName": "DLC4Recon",
      "getglobalpercentage": 7.9,
      "difficulty": 3
    },
    {
      "name": "Festival of Blood",
      "description": "Save Serka.",
      "imageUrl": "https://steamcdn-a.akamaihd.net/steamcommunity/public/images/apps/356190/9cf85cc745db20651f1ae4f904dfd488cb720fb0.jpg",
      "hidden": 0,
      "id": 64,
      "unlocked": false,
      "apiName": "DLC4Rescue",
      "getglobalpercentage": 7.3,
      "difficulty": 3
    },
    {
      "name": "Point of No Return",
      "description": "Defend the Oasis.",
      "imageUrl": "https://steamcdn-a.akamaihd.net/steamcommunity/public/images/apps/356190/d4b7c6fa872832db745246818015105a012a04a2.jpg",
      "hidden": 0,
      "id": 65,
      "unlocked": false,
      "apiName": "DLC4Oasis",
      "getglobalpercentage": 6.7,
      "difficulty": 3
    },
    {
      "name": "Reap What You Sow",
      "description": "Conquer the Fortress of Shindrâm as Baranor.",
      "imageUrl": "https://steamcdn-a.akamaihd.net/steamcommunity/public/images/apps/356190/1d30967ce5a3ea3b63fd9cb2a2f2649454523272.jpg",
      "hidden": 0,
      "id": 66,
      "unlocked": false,
      "apiName": "DLC4Finale",
      "getglobalpercentage": 6.5,
      "difficulty": 3
    },
    {
      "name": "Baranor the Conqueror",
      "description": "Complete the Desolation of Mordor with a Gold Rating.",
      "imageUrl": "https://steamcdn-a.akamaihd.net/steamcommunity/public/images/apps/356190/a00194fa35233d8f31534467121f13e1020bb2db.jpg",
      "hidden": 0,
      "id": 67,
      "unlocked": false,
      "apiName": "DLC4HighScore",
      "getglobalpercentage": 2.1,
      "difficulty": 4
    },
    {
      "name": "Gauntlet",
      "description": "Collect all Númenórean artifacts and bring them to Torvin.",
      "imageUrl": "https://steamcdn-a.akamaihd.net/steamcommunity/public/images/apps/356190/49ae14d3e027ceaa2834593fd26b2cddfab8f13d.jpg",
      "hidden": 0,
      "id": 68,
      "unlocked": false,
      "apiName": "DLC4TorvinSkills",
      "getglobalpercentage": 4.7,
      "difficulty": 4
    },
    {
      "name": "Bombardier",
      "description": "Kill at least one enemy with each ammo type while gliding as Baranor.",
      "imageUrl": "https://steamcdn-a.akamaihd.net/steamcommunity/public/images/apps/356190/bc953fea8f2d985b80f3a7d5ee4326cf32c2b6c4.jpg",
      "hidden": 0,
      "id": 69,
      "unlocked": false,
      "apiName": "DLC4AerialKills",
      "getglobalpercentage": 1.7,
      "difficulty": 4
    },
    {
      "name": "Eastern Front",
      "description": "Conquer the Fortress of Shindrâm as Talion.",
      "imageUrl": "https://steamcdn-a.akamaihd.net/steamcommunity/public/images/apps/356190/f4e31f661f9818159e260b9ffb1b1e8a3fc2c08d.jpg",
      "hidden": 0,
      "id": 70,
      "unlocked": false,
      "apiName": "DLC4Desert",
      "getglobalpercentage": 17.1,
      "difficulty": 3
    },
    {
      "name": "Shadows of the Sand",
      "description": "Achieve a Gold Rating on all Shadow of the Past missions in Lithlad.",
      "imageUrl": "https://steamcdn-a.akamaihd.net/steamcommunity/public/images/apps/356190/fe5af9bf85b74d5b5bb8588f4562809964b53587.jpg",
      "hidden": 0,
      "id": 71,
      "unlocked": false,
      "apiName": "DLC4SOTPDesert",
      "getglobalpercentage": 3.2,
      "difficulty": 4
    }
  ]
}