{
  "name": "King of Seas",
  "platform": "GOG",
  "imageUrl": "",
  "description": "",
  "method": "GOG API",
  "appid": 1105915912,
  "achievements": [
    {
      "name": "King of Gold",
      "description": "Earn 500.000 gold",
      "imageUrl": "https://images.gog.com/28d9ed27e15206f0e0c88c29b8297f016cb01096766448e27607d337dcf472cb_gac_60.jpg",
      "hidden": 0,
      "id": 0,
      "unlocked": false,
      "apiName": "ACHIEVEMENT_00",
      "getglobalpercentage": 0,
      "difficulty": 0
    },
    {
      "name": "This is the life for me",
      "description": "Complete your first game",
      "imageUrl": "https://images.gog.com/d4925831212c3379b2ecdd1f5e34754e4f973d0bd7d8ba5d75eaafb61d6e8497_gac_60.jpg",
      "hidden": 0,
      "id": 0,
      "unlocked": false,
      "apiName": "ACHIEVEMENT_01",
      "getglobalpercentage": 0,
      "difficulty": 0
    },
    {
      "name": "Easy as pie",
      "description": "Complete the game in Ship\u0027s boy difficulty",
      "imageUrl": "https://images.gog.com/e759859f565b3984755f17fa760cdf0797bee1184d2a635a4c99e58cfc6e2b0a_gac_60.jpg",
      "hidden": 0,
      "id": 0,
      "unlocked": false,
      "apiName": "ACHIEVEMENT_02",
      "getglobalpercentage": 0,
      "difficulty": 0
    },
    {
      "name": "Aye aye, Sir!",
      "description": "Complete the game in Gunner difficulty",
      "imageUrl": "https://images.gog.com/6e29a0ea7e456a69dc541ae02b0e08a8fb17afbc60c1d21e91d49242a3b62ce8_gac_60.jpg",
      "hidden": 0,
      "id": 0,
      "unlocked": false,
      "apiName": "ACHIEVEMENT_03",
      "getglobalpercentage": 0,
      "difficulty": 0
    },
    {
      "name": "Caribbean seadog",
      "description": "Complete the game in Captain difficulty",
      "imageUrl": "https://images.gog.com/5cf7f20226a7e802bfd832af42ee110d62e6814f4d2c0c52f9ef17c14677953b_gac_60.jpg",
      "hidden": 0,
      "id": 0,
      "unlocked": false,
      "apiName": "ACHIEVEMENT_04",
      "getglobalpercentage": 0,
      "difficulty": 0
    },
    {
      "name": "Corsair of the fleet",
      "description": "Complete the game in Corsair difficulty",
      "imageUrl": "https://images.gog.com/912a4238b9b1abb1e8d6f8ef80a798d073d05f454c10b2ca574ebaee6effb489_gac_60.jpg",
      "hidden": 0,
      "id": 0,
      "unlocked": false,
      "apiName": "ACHIEVEMENT_05",
      "getglobalpercentage": 0,
      "difficulty": 0
    },
    {
      "name": "King of Seas",
      "description": "Complete the game in King of Seas difficulty",
      "imageUrl": "https://images.gog.com/265baf03007ebe4365ee532020a3aa02bbf48550cd135a16ca298bd324495c9e_gac_60.jpg",
      "hidden": 0,
      "id": 0,
      "unlocked": false,
      "apiName": "ACHIEVEMENT_06",
      "getglobalpercentage": 0,
      "difficulty": 0
    },
    {
      "name": "We\u0027re all in the same boat",
      "description": "Complete 30 side quests",
      "imageUrl": "https://images.gog.com/eaad7c040c1ea705a3e31ee8b357299368c9616b74ad4788710d34f2d99b3e17_gac_60.jpg",
      "hidden": 0,
      "id": 0,
      "unlocked": false,
      "apiName": "ACHIEVEMENT_07",
      "getglobalpercentage": 0,
      "difficulty": 0
    },
    {
      "name": "King of role-playing",
      "description": "Reach the maximum level",
      "imageUrl": "https://images.gog.com/b6c42bdb05a9582043c90a31b5bf996675f894c9091b06c0ad4b4ca9d28bfdff_gac_60.jpg",
      "hidden": 0,
      "id": 0,
      "unlocked": false,
      "apiName": "ACHIEVEMENT_08",
      "getglobalpercentage": 0,
      "difficulty": 0
    },
    {
      "name": "Shiver me timbers!",
      "description": "Find 5 sunken treasures",
      "imageUrl": "https://images.gog.com/ac02a88d8e44d8c591e682d3f4fba1c549916b426ecacc14ec8b2ab3896a20a2_gac_60.jpg",
      "hidden": 0,
      "id": 0,
      "unlocked": false,
      "apiName": "ACHIEVEMENT_09",
      "getglobalpercentage": 0,
      "difficulty": 0
    },
    {
      "name": "In the hold!",
      "description": "Find 10 sunken treasures",
      "imageUrl": "https://images.gog.com/160b411e668635e30b8e7f9cdebb3ed5de2be9665fabf2db16d02c8666f8c0a2_gac_60.jpg",
      "hidden": 0,
      "id": 0,
      "unlocked": false,
      "apiName": "ACHIEVEMENT_10",
      "getglobalpercentage": 0,
      "difficulty": 0
    },
    {
      "name": "King of treasures",
      "description": "Find 30 sunken treasures",
      "imageUrl": "https://images.gog.com/dab048a427a83ad67fbb07a83d80213ce757c7a0fd3f23d114bd9505de2853a3_gac_60.jpg",
      "hidden": 0,
      "id": 0,
      "unlocked": false,
      "apiName": "ACHIEVEMENT_11",
      "getglobalpercentage": 0,
      "difficulty": 0
    },
    {
      "name": "King of lands",
      "description": "Complete the world\u0027s map for the first time",
      "imageUrl": "https://images.gog.com/09a04f1f6294c2247d2079d1b8dda661d73d9ed09ca8d9ddad4f798c17679e08_gac_60.jpg",
      "hidden": 0,
      "id": 0,
      "unlocked": false,
      "apiName": "ACHIEVEMENT_12",
      "getglobalpercentage": 0,
      "difficulty": 0
    },
    {
      "name": "I\u0027m far from done killing",
      "description": "Sink 10 ships",
      "imageUrl": "https://images.gog.com/9a9b6a54e977b6d531e30c17d5f8711f51c53f7510256c4b5339e40bc9304690_gac_60.jpg",
      "hidden": 0,
      "id": 0,
      "unlocked": false,
      "apiName": "ACHIEVEMENT_13",
      "getglobalpercentage": 0,
      "difficulty": 0
    },
    {
      "name": "Blow the men down!",
      "description": "Sink 50 ships",
      "imageUrl": "https://images.gog.com/6ab5a6e673a842bbff012cc186efdd1fe79ee7a0f8fd564c192d6415ec98c25f_gac_60.jpg",
      "hidden": 0,
      "id": 0,
      "unlocked": false,
      "apiName": "ACHIEVEMENT_14",
      "getglobalpercentage": 0,
      "difficulty": 0
    },
    {
      "name": "Scourge of the seas",
      "description": "Sink 100 ships",
      "imageUrl": "https://images.gog.com/56b3cd995521955f08ea710f2a292ceca891b42b2dd285e895bb67b6517d8d83_gac_60.jpg",
      "hidden": 0,
      "id": 0,
      "unlocked": false,
      "apiName": "ACHIEVEMENT_15",
      "getglobalpercentage": 0,
      "difficulty": 0
    },
    {
      "name": "I am the Legend",
      "description": "Sink all Sovereign Pirates",
      "imageUrl": "https://images.gog.com/d9de6cdf2bad74ba4de9388d8815d4cf07f185662ad024eb95dc8ae24a1d9d58_gac_60.jpg",
      "hidden": 0,
      "id": 0,
      "unlocked": false,
      "apiName": "ACHIEVEMENT_16",
      "getglobalpercentage": 0,
      "difficulty": 0
    },
    {
      "name": "Matey!",
      "description": "Conquer 5 enemy settlements",
      "imageUrl": "https://images.gog.com/be30099857bae89c5bc05a37fd2e965a08cf95109d33de443c63fed3c3a9bba7_gac_60.jpg",
      "hidden": 0,
      "id": 0,
      "unlocked": false,
      "apiName": "ACHIEVEMENT_17",
      "getglobalpercentage": 0,
      "difficulty": 0
    },
    {
      "name": "That\u0027s how it\u0027s done!",
      "description": "Conquer 10 enemy settlements",
      "imageUrl": "https://images.gog.com/fcd2d211dfacc39bd505ce332862696649992ccaea4afb82b99a211389c7d441_gac_60.jpg",
      "hidden": 0,
      "id": 0,
      "unlocked": false,
      "apiName": "ACHIEVEMENT_18",
      "getglobalpercentage": 0,
      "difficulty": 0
    },
    {
      "name": "Ah, clear sailing now",
      "description": "Conquer 30 enemy settlements",
      "imageUrl": "https://images.gog.com/5cb5a5061838dd425fc48ee6a1e71c5f20e464d2a043debed7501c35241ffcd3_gac_60.jpg",
      "hidden": 0,
      "id": 0,
      "unlocked": false,
      "apiName": "ACHIEVEMENT_19",
      "getglobalpercentage": 0,
      "difficulty": 0
    },
    {
      "name": "For my hearties",
      "description": "Boost a settlement completely",
      "imageUrl": "https://images.gog.com/d7c0673d38dcfeba0c92fe31f197a4a5edcbf1e5f51932829ee7fd9cdeaf202a_gac_60.jpg",
      "hidden": 0,
      "id": 0,
      "unlocked": false,
      "apiName": "ACHIEVEMENT_20",
      "getglobalpercentage": 0,
      "difficulty": 0
    },
    {
      "name": "Monkey jacket",
      "description": "Earn 1.000 gold from trade",
      "imageUrl": "https://images.gog.com/e499e7e39280815874150e23bc80a5aac36e0c5d1512a35000ec83e6749fb722_gac_60.jpg",
      "hidden": 0,
      "id": 0,
      "unlocked": false,
      "apiName": "ACHIEVEMENT_21",
      "getglobalpercentage": 0,
      "difficulty": 0
    },
    {
      "name": "Gold for my chest",
      "description": "Earn 10.000 gold from trade",
      "imageUrl": "https://images.gog.com/6ce7c30b392d2ef20b8dfd13536afaf55fecc227ed0da9bb46b11e372d0e2b21_gac_60.jpg",
      "hidden": 0,
      "id": 0,
      "unlocked": false,
      "apiName": "ACHIEVEMENT_22",
      "getglobalpercentage": 0,
      "difficulty": 0
    },
    {
      "name": "King of commerce",
      "description": "Earn 100.000 gold from trade",
      "imageUrl": "https://images.gog.com/1034343622e843c6aab116c874eb82481f7d27299479058eb41ca831686fbdae_gac_60.jpg",
      "hidden": 0,
      "id": 0,
      "unlocked": false,
      "apiName": "ACHIEVEMENT_23",
      "getglobalpercentage": 0,
      "difficulty": 0
    },
    {
      "name": "It\u0027 time to loot",
      "description": "Commerce every kind of resource for the first time",
      "imageUrl": "https://images.gog.com/050a03162aa8d9bc7a1023b0774d2ddd5d2654e9c9f2a0d91473b463cc15e8f0_gac_60.jpg",
      "hidden": 0,
      "id": 0,
      "unlocked": false,
      "apiName": "ACHIEVEMENT_24",
      "getglobalpercentage": 0,
      "difficulty": 0
    },
    {
      "name": "Calm waters",
      "description": "Fish successfully 10 times",
      "imageUrl": "https://images.gog.com/da6af1efc167dad188b8c3ce3f5bda28ca00b55e848065bc37b2533e4af6e529_gac_60.jpg",
      "hidden": 0,
      "id": 0,
      "unlocked": false,
      "apiName": "ACHIEVEMENT_25",
      "getglobalpercentage": 0,
      "difficulty": 0
    },
    {
      "name": "Now swab that boat!",
      "description": "Fish successfully 30 times",
      "imageUrl": "https://images.gog.com/8b61de668adfbd9b2070f5bbbc7a4231842b42ca13bc1c03e079e3f0ce302d22_gac_60.jpg",
      "hidden": 0,
      "id": 0,
      "unlocked": false,
      "apiName": "ACHIEVEMENT_26",
      "getglobalpercentage": 0,
      "difficulty": 0
    },
    {
      "name": "And a bunch of cuttlefish for me!",
      "description": "Fish successfully 50 times",
      "imageUrl": "https://images.gog.com/e99d19d12d967cc6bc2477290e124fb823e8de41ebbc05e25d776347d4442f31_gac_60.jpg",
      "hidden": 0,
      "id": 0,
      "unlocked": false,
      "apiName": "ACHIEVEMENT_27",
      "getglobalpercentage": 0,
      "difficulty": 0
    },
    {
      "name": "Fisherman King",
      "description": "Find every kind of fish for the first time",
      "imageUrl": "https://images.gog.com/e13e40bc1d4d52f2ec18c323a1fc9067ce18cbd37522616eb8046848060742df_gac_60.jpg",
      "hidden": 0,
      "id": 0,
      "unlocked": false,
      "apiName": "ACHIEVEMENT_28",
      "getglobalpercentage": 0,
      "difficulty": 0
    }
  ]
}